otg_mcp/.python-version
otg_mcp/__init__.py
otg_mcp/__main__.py
otg_mcp/client.py
otg_mcp/client_capture.py
otg_mcp/config.py
otg_mcp/py.typed
otg_mcp/schema_registry.py
otg_mcp/server.py
otg_mcp/models/__init__.py
otg_mcp/models/models.py
otg_mcp/schemas/1_28_0/openapi.yaml
otg_mcp/schemas/1_29_0/openapi.yaml
otg_mcp/schemas/1_30_0/openapi.yaml
otg_mcp-1.0.dist-info/METADATA
otg_mcp-1.0.dist-info/WHEEL
otg_mcp-1.0.dist-info/licenses/LICENSE
otg_mcp-1.0.dist-info/RECORD
