Metadata-Version: 2.4
Name: otg-mcp
Version: 1.0
Summary: Open Traffic Generator - Model Context Protocol
Author: OTG MCP Contributors
License-File: LICENSE
Requires-Python: >=3.11
Requires-Dist: fastmcp>=2.2.5
Requires-Dist: httpx>=0.24.1
Requires-Dist: mcp[cli]>=1.6.0
Requires-Dist: modelcontextprotocol>=0.1.0
Requires-Dist: pydantic-settings>=2.0.0
Requires-Dist: pydantic>=2.0.0
Requires-Dist: snappi>=1.28.2
Requires-Dist: tenacity>=8.2.2
Requires-Dist: types-pyyaml>=6.0.12.20250516
Provides-Extra: all
Requires-Dist: black>=25.1.0; extra == 'all'
Requires-Dist: mypy>=1.0.0; extra == 'all'
Requires-Dist: openapi-python-client>=0.14.0; extra == 'all'
Requires-Dist: pip>=25.1.1; extra == 'all'
Requires-Dist: pytest-asyncio>=0.21.0; extra == 'all'
Requires-Dist: pytest-cov>=4.0.0; extra == 'all'
Requires-Dist: pytest>=7.0.0; extra == 'all'
Requires-Dist: ruff>=0.11.7; extra == 'all'
Provides-Extra: dev
Requires-Dist: black>=25.1.0; extra == 'dev'
Requires-Dist: mypy>=1.0.0; extra == 'dev'
Requires-Dist: openapi-python-client>=0.14.0; extra == 'dev'
Requires-Dist: pip>=25.1.1; extra == 'dev'
Requires-Dist: ruff>=0.11.7; extra == 'dev'
Provides-Extra: test
Requires-Dist: pytest-asyncio>=0.21.0; extra == 'test'
Requires-Dist: pytest-cov>=4.0.0; extra == 'test'
Requires-Dist: pytest>=7.0.0; extra == 'test'
